pyrnnoise-0.4.3.data/purelib/pyrnnoise/__init__.py
pyrnnoise-0.4.3.data/purelib/pyrnnoise/cli.py
pyrnnoise-0.4.3.data/purelib/pyrnnoise/librnnoise.so
pyrnnoise-0.4.3.data/purelib/pyrnnoise/pyrnnoise.py
pyrnnoise-0.4.3.data/purelib/pyrnnoise/rnnoise.py
pyrnnoise-0.4.3.dist-info/licenses/LICENSE
pyrnnoise-0.4.3.dist-info/METADATA
pyrnnoise-0.4.3.dist-info/WHEEL
pyrnnoise-0.4.3.dist-info/entry_points.txt
pyrnnoise-0.4.3.dist-info/top_level.txt
pyrnnoise-0.4.3.dist-info/RECORD
