Metadata-Version: 2.4
Name: pyrnnoise
Version: 0.4.3
Summary: PyRnNoise
Home-page: https://github.com/pengzhendong/pyrnnoise
Author: Zhendong Peng
Author-email: pzd17@tsinghua.org.cn
Classifier: Programming Language :: Python :: 3
Classifier: Operating System :: OS Independent
Classifier: Topic :: Scientific/Engineering
License-File: LICENSE
Requires-Dist: audiolab
Requires-Dist: click
Requires-Dist: matplotlib
Requires-Dist: numpy
Requires-Dist: tqdm
Dynamic: author
Dynamic: author-email
Dynamic: classifier
Dynamic: description
Dynamic: description-content-type
Dynamic: home-page
Dynamic: license-file
Dynamic: requires-dist
Dynamic: summary
